pttn/__init__.py
pttn/_modidx.py
pttn/cons.py
pttn/snek.py
pttn/util.py
pttn-0.0.8.dist-info/LICENSE
pttn-0.0.8.dist-info/METADATA
pttn-0.0.8.dist-info/WHEEL
pttn-0.0.8.dist-info/entry_points.txt
pttn-0.0.8.dist-info/top_level.txt
pttn-0.0.8.dist-info/RECORD
