Metadata-Version: 2.1
Name: pttn
Version: 0.0.8
Summary: chaos package of utilities; a nod to pttnlith
Home-page: https://github.com/dsm-72/pttn
Author: dsm-72
Author-email: sumner.magruder@yale.edu
License: Apache Software License 2.0
Keywords: nbdev jupyter notebook python
Classifier: Development Status :: 4 - Beta
Classifier: Intended Audience :: Developers
Classifier: Natural Language :: English
Classifier: Programming Language :: Python :: 3.11
Classifier: License :: OSI Approved :: Apache Software License
Requires-Python: >=3.11
License-File: LICENSE
Requires-Dist: atyp
Requires-Dist: nchr
Requires-Dist: nlit
Requires-Dist: pfmt
Requires-Dist: putl
Requires-Dist: asto
Requires-Dist: chck
Provides-Extra: dev
